MicrosoftSqlHelper/__init__.py
MicrosoftSqlHelper/MSSqlHelper.py
microsoftsqlhelper-0.1.1.dist-info/METADATA
microsoftsqlhelper-0.1.1.dist-info/WHEEL
microsoftsqlhelper-0.1.1.dist-info/RECORD
